gblinks
