Metadata-Version: 1.1
Name: gblinks
Version: 0.3.4
Summary: Python tool to find out broken GitBook links
Home-page: https://github.com/davidmogar/gblinks
Author: David Moreno García
Author-email: david.mogar@gmail.com
License: MIT license
Keywords: gblinks
Platform: UNKNOWN
Classifier: Development Status :: 2 - Pre-Alpha
Classifier: Intended Audience :: Developers
Classifier: License :: OSI Approved :: MIT License
Classifier: Natural Language :: English
Classifier: Programming Language :: Python :: 2
Classifier: Programming Language :: Python :: 2.6
Classifier: Programming Language :: Python :: 2.7
Classifier: Programming Language :: Python :: 3
Classifier: Programming Language :: Python :: 3.3
Classifier: Programming Language :: Python :: 3.4
Classifier: Programming Language :: Python :: 3.5
